lazy_nessus/__about__.py
lazy_nessus/__init__.py
lazy_nessus/main.py
lazy_nessus/scans/actions/check.py
lazy_nessus/scans/actions/export.py
lazy_nessus/scans/actions/list.py
lazy_nessus/scans/actions/pause.py
lazy_nessus/scans/actions/resume.py
lazy_nessus/scans/actions/search.py
lazy_nessus/utils/spinner.py
lazy_nessus-0.2.6.post2.dist-info/METADATA
lazy_nessus-0.2.6.post2.dist-info/WHEEL
lazy_nessus-0.2.6.post2.dist-info/entry_points.txt
lazy_nessus-0.2.6.post2.dist-info/licenses/LICENSE
lazy_nessus-0.2.6.post2.dist-info/RECORD
